literature/__init__.py
literature/admin.py
literature/api/__init__.py
literature/api/serialize.py
literature/api/views.py
literature/apps.py
literature/choices.py
literature/conf.py
literature/csl_map.py
literature/drf.py
literature/fields.py
literature/forms.py
literature/formset.py
literature/managers.py
literature/migrations/__init__.py
literature/models.py
literature/static/literature/icons/icons.svg
literature/static/literature/icons/three-dots.svg
literature/static/literature/js/admin/change_list.js
literature/static/literature/js/datatablesHyperlink.js
literature/static/literature/js/main copy.js
literature/static/literature/js/main.js
literature/static/vendor/DataTables/bootstrap4/datatables.min.css
literature/static/vendor/DataTables/bootstrap4/datatables.min.js
literature/static/vendor/DataTables/bootstrap5/datatables.min.css
literature/static/vendor/DataTables/bootstrap5/datatables.min.js
literature/static/vendor/DataTables/datatables/datatables.min.css
literature/static/vendor/DataTables/datatables/datatables.min.js
literature/static/vendor/js/citation.js
literature/templates/base.html
literature/templates/literature/admin/change_list.html
literature/templates/literature/admin/search.html
literature/templates/literature/author_detail.html
literature/templates/literature/author_list.html
literature/templates/literature/bibliography.html
literature/templates/literature/citation/bootstrap.html
literature/templates/literature/citation/plain_text.html
literature/templates/literature/literature_detail.html
literature/templates/literature/literature_form.html
literature/templates/literature/literature_form1.html
literature/templates/literature/literature_list.html
literature/templates/literature/widgets/identifier.html
literature/templates/literature/widgets/pdf_viewer.html
literature/templates/literature/widgets/postgres_array_widget.html
literature/templates/literature/widgets/preview.html
literature/templatetags/__init__.py
django_literature-0.1.7.dist-info/LICENSE
django_literature-0.1.7.dist-info/METADATA
django_literature-0.1.7.dist-info/WHEEL
django_literature-0.1.7.dist-info/RECORD
