Metadata-Version: 2.1
Name: django-literature
Version: 0.1.7
Summary: A scientific literature management tool for Django
Home-page: https://github.com/SSJenny90/django-literature
License: MIT
Keywords: django,literature,publications,scientific,research
Author: Sam Jennings
Author-email: samuel.scott.jennings@gmail.com
Requires-Python: >=3.8,<4.0
Classifier: Development Status :: 3 - Alpha
Classifier: Framework :: Django :: 3.2
Classifier: Intended Audience :: Developers
Classifier: License :: OSI Approved :: BSD License
Classifier: License :: OSI Approved :: MIT License
Classifier: Natural Language :: English
Classifier: Programming Language :: Python :: 3
Classifier: Programming Language :: Python :: 3.8
Classifier: Programming Language :: Python :: 3.9
Classifier: Programming Language :: Python :: 3.10
Classifier: Programming Language :: Python :: 3.11
Requires-Dist: django (>=3.2)
Requires-Dist: django-appconf (>=1.0.5,<2.0.0)
Requires-Dist: django-formset (>=1.0,<2.0)
Requires-Dist: django-model-utils (>=4.3.1,<5.0.0)
Requires-Dist: django-sortedm2m (>=3.1.1,<4.0.0)
Requires-Dist: django-taggit (>=3.1.0,<4.0.0)
Requires-Dist: djangorestframework (>=3.14.0,<4.0.0)
Requires-Dist: drf-schema-adapter (>=3.0.6,<4.0.0)
Requires-Dist: python-dateutil (>=2.8.2,<3.0.0)
